{
  "name": "Autumn Pixie",
  "icon": "feywild:summoning_scroll_autumn_pixie",
  "category": "pixies",
  "pages": [
    {
      "type": "text",
      "text": "The Autumn Court is the most mature of the four Fey Courts, their age and wisdom has given them a appreciation of fine art, music and poetry. They rather spend a night listening to song, dancing and flirting then going to combat or mindlessly indulging themselves."
    },
    {
      "type": "entity",
      "entity": "feywild:autumn_pixie",
      "offset": 0.4
    }
  ]
}