{
  "parent": "feywild:adventure/dwarf_trade",
  "display": {
    "icon": {
      "item": "feywild:feywild_lexicon"
    },
    "title": "Welcome to the Feywild",
    "description": "You borrowed the Feywild Lexicon from the Library",
    "frame": "goal",
    "show_toast": true,
    "announce_to_chat": true,
    "hidden": false
  },
  "criteria": {
    "borrowed": {
      "trigger": "minecraft:inventory_changed",
      "conditions": {
        "items": [
          {
            "item": "feywild:feywild_lexicon"
          }
        ]
      }
    }
  },
  "requirements": [
    [
      "borrowed"
    ]
  ]
}